digiCore/__init__.py
digiCore/dsd_kafka.py
digiCore/dsd_mongodb.py
digiCore/dsd_mysql.py
digiCore/dsd_redis.py
digiCore/status_code.py
digiCore/dingding/__init__.py
digiCore/dingding/dingding_model.py
digiCore/dingding/send_to_group.py
digiCore/kingdee/__init__.py
digiCore/kingdee/kingdee_tools.py
digiCore/lingxing/__init__.py
digiCore/lingxing/api_scheduler.py
digiCore/test/__init__.py
digiCore/utils/__init__.py
digiCore/utils/utils.py
DigiCore-1.0.1.dist-info/LICENSE
DigiCore-1.0.1.dist-info/METADATA
DigiCore-1.0.1.dist-info/WHEEL
DigiCore-1.0.1.dist-info/top_level.txt
DigiCore-1.0.1.dist-info/zip-safe
DigiCore-1.0.1.dist-info/RECORD
